loadmydata/__init__.py
loadmydata/config.py
loadmydata/load_uea_ucr.py
loadmydata/utils.py
loadmydata-0.0.3.dist-info/LICENSE
loadmydata-0.0.3.dist-info/METADATA
loadmydata-0.0.3.dist-info/WHEEL
loadmydata-0.0.3.dist-info/top_level.txt
loadmydata-0.0.3.dist-info/zip-safe
loadmydata-0.0.3.dist-info/RECORD
