Metadata-Version: 2.1
Name: loadmydata
Version: 0.0.3
Summary: Collections of utility functions to download open-source data sets.
Home-page: https://github.com/deepcharles/loadmydata
Author: Charles T.
Author-email: charles@doffy.net
License: BSD-2-Clause
Project-URL: Bug Tracker, https://github.com/deepcharles/loadmydata/issues
Platform: UNKNOWN
Requires-Python: >=3.6
Requires-Dist: pandas
Requires-Dist: requests
Requires-Dist: sktime
Requires-Dist: tqdm
Requires-Dist: yarl
